chaos_python/__init__.py
chaos_python/client.py
Chaos_Python_Client-1.0.0.dist-info/LICENSE.md
Chaos_Python_Client-1.0.0.dist-info/METADATA
Chaos_Python_Client-1.0.0.dist-info/WHEEL
Chaos_Python_Client-1.0.0.dist-info/top_level.txt
Chaos_Python_Client-1.0.0.dist-info/RECORD
