Metadata-Version: 2.1
Name: Chaos-Python-Client
Version: 1.0.0
Summary: [Unofficial] Python client for contacting with chaos API
Home-page: https://github.com/arkwrn/chaos-python
Author: Arie Kurniawan
Author-email: hubungi.aja@gmail.com
License: UNKNOWN
Platform: UNKNOWN
Classifier: Programming Language :: Python :: 3
Classifier: License :: OSI Approved :: MIT License
Classifier: Operating System :: OS Independent
Requires-Python: >=3
